MANIFEST.in
setup.cfg
setup.py
docs/CHANGES.txt
docs/HISTORY.txt
docs/Makefile
docs/README.txt
docs/conf.py
docs/general.rst
docs/index.rst
docs/index2.rst
docs/make.bat
docs/restful.pt
quantumcore/__init__.py
quantumcore.storages.egg-info/PKG-INFO
quantumcore.storages.egg-info/SOURCES.txt
quantumcore.storages.egg-info/dependency_links.txt
quantumcore.storages.egg-info/entry_points.txt
quantumcore.storages.egg-info/namespace_packages.txt
quantumcore.storages.egg-info/not-zip-safe
quantumcore.storages.egg-info/paster_plugins.txt
quantumcore.storages.egg-info/requires.txt
quantumcore.storages.egg-info/top_level.txt
quantumcore/storages/__init__.py
quantumcore/storages/attributemapper.py
quantumcore/storages/exc.py
quantumcore/storages/extendedfilestore.py
quantumcore/storages/filesystem.py
quantumcore/storages/memorymappingstore.py
quantumcore/storages/mongomappingstore.py
quantumcore/storages/mongoobjectstore.py
quantumcore/storages/utils.py
quantumcore/storages/tests/__init__.py
quantumcore/storages/tests/conftest.py
quantumcore/storages/tests/test_attributemapper.py
quantumcore/storages/tests/test_basics.py
quantumcore/storages/tests/test_extendedfilestore.py
quantumcore/storages/tests/test_filesystemstore.py
quantumcore/storages/tests/test_memorymappingstore.py
quantumcore/storages/tests/test_mongomappingstore.py