Metadata-Version: 1.0
Name: quantumcore.storages
Version: 0.007
Summary: A collection of storage modules like for file management, metadata and more
Home-page: http://quantumcore.org
Author: Christian Scholz et al
Author-email: cs@comlounge.net
License: MIT
Keywords: quantumcore storages mongodb metadata assets assetmanagement filesystem files
Platform: UNKNOWN
Classifier: Programming Language :: Python
Classifier: Topic :: Software Development :: Libraries :: Python Modules
Classifier: Development Status :: 4 - Beta
Classifier: Environment :: Web Environment
Classifier: Intended Audience :: Developers
Classifier: License :: OSI Approved :: MIT License
Classifier: Operating System :: OS Independent
Classifier: Topic :: Internet :: WWW/HTTP :: WSGI
Classifier: Topic :: Internet :: WWW/HTTP
Classifier: Topic :: Utilities
